{
  "vpc-provider:account=464015903663:filter.vpc-id=vpc-0216c91a9f09136b7:region=us-west-2:returnAsymmetricSubnets=true": {
    "vpcId": "vpc-0216c91a9f09136b7",
    "vpcCidrBlock": "172.31.0.0/16",
    "ownerAccountId": "464015903663",
    "availabilityZones": [],
    "subnetGroups": [
      {
        "name": "Public",
        "type": "Public",
        "subnets": [
          {
            "subnetId": "subnet-074324bfa28b458ea",
            "cidr": "172.31.0.0/20",
            "availabilityZone": "us-west-2a",
            "routeTableId": "rtb-0311e9e2a62b74b5a"
          },
          {
            "subnetId": "subnet-0215f17a230dc164a",
            "cidr": "172.31.16.0/20",
            "availabilityZone": "us-west-2b",
            "routeTableId": "rtb-0311e9e2a62b74b5a"
          }
        ]
      },
      {
        "name": "Isolated",
        "type": "Isolated",
        "subnets": [
          {
            "subnetId": "subnet-0cd8de2fb63b992ac",
            "cidr": "172.31.128.0/20",
            "availabilityZone": "us-west-2a",
            "routeTableId": "rtb-0b73aed9a3f165ca6"
          },
          {
            "subnetId": "subnet-0e0d237bade9df688",
            "cidr": "172.31.144.0/20",
            "availabilityZone": "us-west-2b",
            "routeTableId": "rtb-04d82a3694117d625"
          }
        ]
      }
    ]
  },
  "ami:account=464015903663:filters.image-type.0=machine:filters.name.0=aws-storage-gateway*:filters.state.0=available:region=us-west-2": "ami-063ffea8ceb0c5923"
}
